prompt_enhancer/__init__.py
prompt_enhancer/enhancer.py
PromptPrompter-0.1.3.dist-info/LICENSE
PromptPrompter-0.1.3.dist-info/METADATA
PromptPrompter-0.1.3.dist-info/WHEEL
PromptPrompter-0.1.3.dist-info/top_level.txt
PromptPrompter-0.1.3.dist-info/RECORD
