Metadata-Version: 2.2
Name: PromptPrompter
Version: 0.1.3
Summary: A Python package for prompt enhancement and multi-model interaction with OpenAI and Gemini.
Author-email: Roni Can Şahin <sahin.ronican@gmail.com>
Project-URL: Homepage, https://github.com/Ronican/PromptPrompter
Project-URL: Bug Tracker, https://github.com/Ronican/PromptPrompter/issues
Classifier: Programming Language :: Python :: 3
Classifier: License :: OSI Approved :: MIT License
Classifier: Operating System :: OS Independent
Requires-Python: >=3.7
License-File: LICENSE
Requires-Dist: requests
Requires-Dist: httpx
Requires-Dist: google-generativeai
Requires-Dist: openai
